llama_index/llms/langchain/__init__.py
llama_index/llms/langchain/base.py
llama_index/llms/langchain/utils.py
llama_index_llms_langchain-0.7.0.dist-info/METADATA
llama_index_llms_langchain-0.7.0.dist-info/WHEEL
llama_index_llms_langchain-0.7.0.dist-info/licenses/LICENSE
llama_index_llms_langchain-0.7.0.dist-info/RECORD
