Metadata-Version: 2.4
Name: llama-index-llms-langchain
Version: 0.7.0
Summary: llama-index llms langchain integration
Author-email: Your Name <you@example.com>
License-Expression: MIT
License-File: LICENSE
Requires-Python: <4.0,>=3.9
Requires-Dist: langchain>=0.1.7
Requires-Dist: llama-index-core<0.14,>=0.13.0
